setup.py
client/__init__.py
client/add_contact_window.py
client/client_main_window.py
client/cln_db.py
client/del_contact_window.py
client/start_dialog.py
common/__init__.py
common/constant.py
common/decorators.py
common/descriptors.py
common/messanger.py
common/meta.py
msg_cln.egg-info/PKG-INFO
msg_cln.egg-info/SOURCES.txt
msg_cln.egg-info/dependency_links.txt
msg_cln.egg-info/requires.txt
msg_cln.egg-info/top_level.txt
unit_tests/__init__.py
unit_tests/test_client.py
unit_tests/test_messanger.py
unit_tests/test_server.py