Metadata-Version: 1.0
Name: msg-cln
Version: 0.0.1
Summary: messenger client part
Home-page: UNKNOWN
Author: Oleg Lo
Author-email: olomakin@ya.ru
License: UNKNOWN
Platform: UNKNOWN
